uncwrap/__init__.py
uncwrap/__main__.py
uncwrap/_version.py
uncwrap/classifier_uncertainty.py
uncwrap/cli.py
uncwrap/examples/Uncertainty Wrapper Example (20 newsgroups to BBC news).ipynb
uncwrap/examples/Uncertainty_Toy_problem_3classes.ipynb
uncwrap/examples/Uncertainty_Toy_problem_3classes_OOD.ipynb
uncwrap/examples/newsgroups_2_politics_example.py
uncwrap/models/__init__.py
uncwrap/models/dirichlet_wrapper.py
uncwrap/tests/__init__.py
uncwrap/tests/conftest.py
uncwrap/tests/fixtures/bbc-text.csv
uncwrap/tests/test_classifier_uncertainty.py
uncwrap/tests/test_utils.py
uncwrap-0.5.dist-info/entry_points.txt
uncwrap-0.5.dist-info/LICENSE
uncwrap-0.5.dist-info/LICENSE.md
uncwrap-0.5.dist-info/WHEEL
uncwrap-0.5.dist-info/METADATA
uncwrap-0.5.dist-info/RECORD
