Metadata-Version: 2.1
Name: uncwrap
Version: 0.5
Summary: Sklearn wrapper for classifications system that computes the prediction uncertainty
Home-page: https://github.com/menajosep/uncertainty_modeller
License: MIT
Author: José Mena
Author-email: menajosep@gmail.com
Requires-Python: >=3.7.1,<4.0.0
Classifier: Development Status :: 1 - Planning
Classifier: License :: OSI Approved :: MIT License
Classifier: Natural Language :: English
Classifier: Operating System :: OS Independent
Classifier: Programming Language :: Python
Classifier: Programming Language :: Python :: 3
Classifier: Programming Language :: Python :: 3.10
Classifier: Programming Language :: Python :: 3.7
Classifier: Programming Language :: Python :: 3.8
Classifier: Programming Language :: Python :: 3.9
Requires-Dist: click (==7.1.2)
Requires-Dist: minilog (==1.6)
Requires-Dist: numpy (==1.19.2)
Requires-Dist: pandas (==1.1.3)
Requires-Dist: protobuf (>=3.19.0,<4.0.0)
Requires-Dist: scikit-learn (==0.23.2)
Requires-Dist: scipy (==1.5.2)
Requires-Dist: tensorflow (==1.15.2)
Requires-Dist: tensorflow-probability (==0.7.0)
Project-URL: Documentation, https://github.com/menajosep/uncertainty_modeller/README.md
